microfs/__init__.py
microfs/__init__.pyi
microfs/__main__.py
microfs/lib.py
microfs/lib.pyi
microfs/main.py
microfs/main.pyi
microfs/py.typed
microfs2-2.0.7.dist-info/licenses/AUTHORS
microfs2-2.0.7.dist-info/licenses/LICENSE
microfs2-2.0.7.dist-info/METADATA
microfs2-2.0.7.dist-info/WHEEL
microfs2-2.0.7.dist-info/entry_points.txt
microfs2-2.0.7.dist-info/top_level.txt
microfs2-2.0.7.dist-info/RECORD
