Metadata-Version: 2.4
Name: microfs2
Version: 2.0.7
Summary: A module and utility to work with the simple filesystem on the BBC micro:bit
Author-email: Blackteahamburger <blackteahamburger@outlook.com>
Maintainer-email: Blackteahamburger <blackteahamburger@outlook.com>
License-Expression: MIT
Project-URL: Homepage, https://github.com/blackteahamburger/microfs
Classifier: Development Status :: 5 - Production/Stable
Classifier: Environment :: Console
Classifier: Intended Audience :: Developers
Classifier: Intended Audience :: Education
Classifier: Operating System :: Microsoft :: Windows
Classifier: Operating System :: POSIX
Classifier: Programming Language :: Python :: 3.11
Classifier: Programming Language :: Python :: 3.12
Classifier: Programming Language :: Python :: 3.13
Classifier: Programming Language :: Python :: 3.14
Classifier: Topic :: Education
Classifier: Topic :: Software Development :: Embedded Systems
Requires-Python: >=3.11
License-File: AUTHORS
License-File: LICENSE
Requires-Dist: pyserial<4.0,>=3.0.1
Dynamic: license-file
